trimcts-1.3.0.dist-info/WHEEL
trimcts-1.3.0.dist-info/RECORD
trimcts-1.3.0.dist-info/top_level.txt
trimcts-1.3.0.dist-info/METADATA
trimcts-1.3.0.dist-info/licenses/LICENSE
trimcts/README.md
trimcts/py.typed
trimcts/mcts_wrapper.py
trimcts/config.py
trimcts/__init__.py
trimcts/trimcts_cpp.cpython-37m-x86_64-linux-gnu.so
trimcts/trimcts_cpp.cpython-312-x86_64-linux-gnu.so
trimcts/cpp/mcts_manager.cpp
trimcts/cpp/mcts.h
trimcts/cpp/README.md
trimcts/cpp/bindings.cpp
trimcts/cpp/config.h
trimcts/cpp/CMakeLists.txt
trimcts/cpp/python_interface.h
trimcts/cpp/mcts.cpp
trimcts/cpp/mcts_manager.h
