Metadata-Version: 2.4
Name: trimcts
Version: 1.3.0
Summary: High‑performance C++ MCTS (AlphaZero & MuZero) with Tree Reuse and Avg Depth for triangular games
Author-email: "Luis Guilherme P. M." <lgpelin92@gmail.com>
License-Expression: MIT
Project-URL: Homepage, https://github.com/lguibr/trimcts
Project-URL: Bug Tracker, https://github.com/lguibr/trimcts/issues
Classifier: Development Status :: 4 - Beta
Classifier: Intended Audience :: Developers
Classifier: Programming Language :: Python :: 3.10
Classifier: Programming Language :: C++
Requires-Python: >=3.10
License-File: LICENSE
Requires-Dist: numpy>=1.20.0
Requires-Dist: pydantic>=2.0.0
Requires-Dist: trianglengin>=2.0.6
Provides-Extra: dev
Requires-Dist: pytest>=7.0; extra == "dev"
Requires-Dist: pytest-cov; extra == "dev"
Requires-Dist: ruff; extra == "dev"
Requires-Dist: mypy; extra == "dev"
Dynamic: license-file
